wudi.py
wudi-0.0.2.dist-info/DESCRIPTION.rst
wudi-0.0.2.dist-info/METADATA
wudi-0.0.2.dist-info/RECORD
wudi-0.0.2.dist-info/WHEEL
wudi-0.0.2.dist-info/metadata.json
wudi-0.0.2.dist-info/top_level.txt
