Metadata-Version: 2.0
Name: wudi
Version: 0.0.2
Summary: wudi script
Home-page: http://www.zhaomingming.cn
Author: zhaomingming
Author-email: 13271929138@163.com
License: MIT
Platform: any
